<?xml version="1.0"?>
<!DOCTYPE hibernate-mapping PUBLIC "-//Hibernate/Hibernate Mapping DTD 3.0//EN"
"http://www.hibernate.org/dtd/hibernate-mapping-3.0.dtd">
<hibernate-mapping>
    <class name="inventario.Inventario_his" table="INV02_log">
  		<id name="id_maquina_log" type="int">
            <column name="id_maquina_log" />
        </id>
        <property name="hostname" type="java.lang.String">
            <column name="hostname" />
        </property>
         <property name="id_maquina" type="int">
            <column name="id_maquina" />
        </property>
        <property name="procesador" type="java.lang.String">
            <column name="procesador" />
        </property>
        <property name="ram" type="java.lang.String">
            <column name="ram" />
        </property>
        <property name="discos" type="java.lang.String">
            <column name="discos" />
        </property>
        <property name="SO" type="java.lang.String">
            <column name="so" />
        </property>
        <property name="licso" type="java.lang.String">
            <column name="licso" />
        </property>        
        <property name="ape" type="java.lang.String">
            <column name="ape" />
        </property>
        <property name="nom" type="java.lang.String">
            <column name="nom" />
        </property>
        <property name="serieso" type="java.lang.String">
            <column name="serieso" />
        </property>
        <property name="aprobocca" type="boolean">
            <column name="aprobocca" />
        </property>
        <property name="aproboccf" type="boolean">
            <column name="aproboccf" />
        </property>
        <property name="cc" type="int">
            <column name="cc" />
        </property>
        <property name="licoffice" type="java.lang.String">
            <column name="licoffice" />
        </property>
        <property name="requerimiento" type="java.lang.String">
            <column name="requerimiento" />
        </property>        
        <property name="usuario" type="java.lang.String">
            <column name="usuario" />
        </property>
        <property name="usuario_log" type="java.lang.String">
            <column name="usuario_log" />
        </property>
        <property name="observaciones" type="java.lang.String">
            <column name="observaciones" />
        </property>
        <property name="estado" type="java.lang.String">
            <column name="estado" />
        </property>
        <property name="fecha_log" type="timestamp">
            <column name="fecha_log" />
        </property>
        <property name="fecha_alta" type="timestamp">
            <column name="fecha_alta" />
        </property>
        <property name="seriesist" type="java.lang.String">
            <column name="seriesist" />
        </property>
        <property name="accion" type="java.lang.String">
            <column name="accion" />
        </property>        
    </class>
</hibernate-mapping>